headers/__init__.py
headers/binary.py
headers/string.py
httpheaders-2024.10.16.dist-info/LICENSE
httpheaders-2024.10.16.dist-info/METADATA
httpheaders-2024.10.16.dist-info/WHEEL
httpheaders-2024.10.16.dist-info/top_level.txt
httpheaders-2024.10.16.dist-info/RECORD
