Metadata-Version: 2.1
Name: httpheaders
Version: 2024.10.16
Summary: HTTP Headers
Home-page: https://github.com/joniumGit/headers
Author: joniumGit
Project-URL: Bug Reports, https://github.com/joniumGit/headers
Project-URL: Source, https://github.com/joniumGit/headers
Keywords: HTTP,headers,API
Classifier: Development Status :: 5 - Production/Stable
Classifier: Intended Audience :: Developers
Classifier: License :: OSI Approved :: MIT License
Classifier: Programming Language :: Python :: 3
Classifier: Topic :: Software Development
Requires-Python: >=3
License-File: LICENSE
